{
  "name": "Trash Panda Theme",
  "dark": true,
  "author": "jasonhulbert",
  "editorScheme": "/trash-panda-theme.xml",
  "colors": {
    "background": "#212527",
    "foreground": "#B1B7BE",
    "altBackground": "#181B1D",
    "altForeground": "#C6CCD3",
    "border": "#383C40",
    "shadow": "#00000000",
    "disabled": "#6A7175",
    "conflict": "#E68680",
    "conflictBackground": "#392120",
    "added": "#14B5A5",
    "addedBackground": "#052D29",
    "deleted": "#E1AB89",
    "deletedBackground": "#382B22",
    "ignored": "#6A7175",
    "ignoredBackground": "#3A3E40",
    "modified": "#20B1D2",
    "modifiedBackground": "#082C34",
    "untracked": "#9586CF",
    "untrackedBackground": "#252134",
    "submodule": "#7A8187",
    "submoduleBackground": "#3A3E40",
    "comment": "#7A8187",
    "black": "#000000",
    "white": "#FFFFFF",
    "accent": "#4A9BF2",
    "accentShade3": "#13273D",
    "accentShade2": "#254E79",
    "accentShade1": "#3874B5",
    "lime": "#A3DEA1",
    "limeShade3": "#293828",
    "limeShade2": "#526F51",
    "limeShade1": "#7AA779",
    "green": "#14B5A5",
    "greenShade3": "#052D29",
    "greenShade2": "#0A5B53",
    "greenShade1": "#0F887C",
    "blue": "#20B1D2",
    "blueShade3": "#082C34",
    "blueShade2": "#105969",
    "blueShade1": "#18859E",
    "cyan": "#7BE1E3",
    "cyanShade3": "#1F3839",
    "cyanShade2": "#3E7172",
    "cyanShade1": "#5CA9AA",
    "purple": "#9586CF",
    "purpleShade3": "#252134",
    "purpleShade2": "#4B4368",
    "purpleShade1": "#70659B",
    "pink": "#DEA6B6",
    "pinkShade3": "#38292E",
    "pinkShade2": "#6F535B",
    "pinkShade1": "#A77D89",
    "red": "#E68680",
    "redShade3": "#392120",
    "redShade2": "#734340",
    "redShade1": "#AD6560",
    "orange": "#E1AB89",
    "orangeShade3": "#382B22",
    "orangeShade2": "#715645",
    "orangeShade1": "#A98067",
    "yellow": "#D8EBA1",
    "yellowShade3": "#363B28",
    "yellowShade2": "#6C7651",
    "yellowShade1": "#A2B079"
  },
  "icons": {
    "ColorPalette": {
      "Actions.Grey": "#7A8187",
      "Actions.Red": "#E68680",
      "Actions.Yellow": "#D8EBA1",
      "Actions.Green": "#14B5A5",
      "Actions.Blue": "#20B1D2",
      "Actions.GreyInline.Dark": "#6A7175",
      "Objects.Grey": "#7A8187",
      "Objects.RedStatus": "#E68680",
      "Objects.Red": "#E68680",
      "Objects.Pink": "#DEA6B6",
      "Objects.Yellow": "#D8EBA1",
      "Objects.Green": "#14B5A5",
      "Objects.Blue": "#20B1D2",
      "Objects.Purple": "#9586CF",
      "Objects.BlackText": "#181B1D",
      "Objects.YellowDark": "#E1AB89",
      "Objects.GreenAndroid": "#A3DEA1",
      "Checkbox.Background.Default.Dark": "#212527",
      "Checkbox.Border.Default.Dark": "#B1B7BE",
      "Checkbox.Foreground.Selected.Dark": "#4A9BF2",
      "Checkbox.Focus.Wide.Dark": "#212527",
      "Checkbox.Focus.Thin.Default.Dark": "#B1B7BE",
      "Checkbox.Focus.Thin.Selected.Dark": "#7BE1E3",
      "Checkbox.Background.Disabled.Dark": "#6A7175",
      "Checkbox.Border.Disabled.Dark": "#6A7175",
      "Checkbox.Foreground.Disabled.Dark": "#6A7175"
    }
  },
  "ui": {
    "*": {
      "windowBorder": "border",
      "background": "background",
      "foreground": "altForeground"
    },
    "Borders": {
      "color": "border",
      "ContrastBorderColor": "border"
    },
    "Button": {
      "arc": 0,
      "foreground": "foreground",
      "background": "background",
      "shadowColor": "shadow",
      "startBackground": "background",
      "endBackground": "background",
      "startBorderColor": "foreground",
      "endBorderColor": "foreground",
      "focusedBorderColor": "foreground",
      "disabledBorderColor": "disabled",
      "disabledText": "disabled",
      "default": {
        "foreground": "accent",
        "shadowColor": "shadow",
        "startBackground": "background",
        "endBackground": "background",
        "startBorderColor": "accent",
        "endBorderColor": "accent",
        "focusColor": "accent",
        "focusedBorderColor": "accent"
      }
    },
    "CheckBox": {
      "background": "background",
      "foreground": "altForeground",
      "select": "accent",
      "disabledText": "disabled"
    },
    "CheckBoxMenuItem": {
      "background": "background"
    },
    "ComboBox": {
      "background": "background",
      "nonEditableBackground": "border",
      "modifiedItemForeground": "modified",
      "ArrowButton": {
        "background": "background",
        "iconColor": "accent",
        "disabledIconColor": "disabled",
        "nonEditableBackground": "border"
      }
    },
    "ComboPopup": {
      "border": "1,1,1,1,383C40"
    },
    "Component": {
      "errorFocusColor": "red",
      "inactiveErrorFocusColor": "redShade1",
      "warningFocusColor": "yellow",
      "inactiveWarningFocusColor": "yellowShade1",
      "iconColor": "foreground",
      "hoverIconColor": "altForeground"
    },
    "Counter": {
      "background": "background",
      "foreground": "altForeground"
    },
    "DebuggerPopup": {
      "borderColor": "border"
    },
    "DefaultTabs": {
      "background": "background",
      "hoverBackground": "altBackground",
      "underlineColor": "accent",
      "inactiveUnderlineColor": "border",
      "underlineHeight": 2,
      "underlinedTabBackground": "altBackground",
      "underlinedTabForeground": "altForeground"
    },
    "DragAndDrop": {
      "areaForeground": "altForeground",
      "areaBackground": "accent",
      "areaBorderColor": "accentShade1"
    },
    "Editor": {
      "background": "background",
      "foreground": "foreground",
      "shortcutForeground": "accent"
    },
    "EditorPane": {
      "inactiveBackground": "background"
    },
    "EditorTabs": {
      "background": "background",
      "underlineColor": "accent",
      "underlineHeight": 2,
      "underlinedTabForeground": "altForeground",
      "underlinedTabBackground": "background",
      "inactiveUnderlineColor": "accentShade2",
      "inactiveColoredFileBackground": "background"
    },
    "FileColor": {
      "Yellow": "yellowShade3",
      "Green": "greenShade3",
      "Blue": "blueShade3",
      "Violet": "purpleShade3",
      "Orange": "orangeShade3",
      "Rose": "pinkShade3"
    },
    "InplaceRefactoringPopup": {
      "borderColor": "border"
    },
    "Link": {
      "activeForeground": "accent",
      "hoverForeground": "accent",
      "pressedForeground": "accent",
      "visitedForeground": "accent",
      "secondaryForeground": "accent"
    },
    "List": {
      "selectionBackground": "accentShade3",
      "selectionForeground": "altForeground"
    },
    "MemoryIndicator": {
      "usedBackground": "blue",
      "allocatedBackground": "purple"
    },
    "Menu": {
      "foreground": "foreground",
      "background": "background",
      "selectionForeground": "altForeground",
      "acceleratorSelectionForeground": "accent",
      "acceleratorForeground": "foreground",
      "borderColor": "border",
      "separatorColor": "border",
      "disabledBackground": "background",
      "disabledForeground": "disabled"
    },
    "NavBar": {
      "borderColor": "border"
    },
    "Notification": {
      "foreground": "foreground",
      "background": "background",
      "borderColor": "accent",
      "errorForeground": "foreground",
      "errorBackground": "background",
      "errorBorderColor": "red",
      "MoreButton": {
        "background": "altBackground",
        "innerBorderColor": "border"
      },
      "ToolWindow": {
        "informativeForeground": "foreground",
        "informativeBackground": "background",
        "informativeBorderColor": "blue",
        "warningForeground": "foreground",
        "warningBackground": "background",
        "warningBorderColor": "orange",
        "errorForeground": "foreground",
        "errorBackground": "background",
        "errorBorderColor": "red"
      }
    },
    "ParameterInfo": {
      "background": "purple",
      "foreground": "background",
      "currentOverloadBackground": "blue",
      "currentParameterForeground": "background"
    },
    "Plugins": {
      "tagBackground": "accent",
      "tagForeground": "altForeground",
      "lightSelectionBackground": "accentShade2",
      "Tab": {
        "selectedBackground": "background",
        "selectedForeground": "altForeground",
        "hoverBackground": "altBackground"
      },
      "SearchField": {
        "borderColor": "border"
      },
      "SectionHeader": {
        "background": "background"
      },
      "Button": {
        "installForeground": "accent",
        "installBorderColor": "accent",
        "installFocusedBackground": "altBackground",
        "installFillForeground": "accent",
        "installFillBackground": "altBackground",
        "updateForeground": "altBackground",
        "updateBackground": "accent"
      }
    },
    "Popup": {
      "paintBorder": true,
      "borderColor": "border",
      "innerBorderColor": "border",
      "inactiveBorderColor": "border",
      "separatorForeground": "border",
      "Toolbar": {
        "background": "background",
        "borderColor": "border"
      },
      "Header": {
        "activeBackground": "background",
        "inactiveBackground": "background"
      },
      "Advertiser": {
        "background": "background",
        "borderColor": "border",
        "borderInsets": "3,8,5,0"
      }
    },
    "PopupMenu": {
      "background": "background",
      "selectionBackground": "accentShade2",
      "borderWidth": 1,
      "borderInsets": "4,1,4,1"
    },
    "ProgressBar": {
      "trackColor": "background",
      "progressColor": "altForeground",
      "indeterminateStartColor": "altForeground",
      "indeterminateEndColor": "background",
      "failedColor": "red",
      "failedEndColor": "redShade2",
      "passedColor": "green",
      "passedEndColor": "greenShade2"
    },
    "ScrollBar": {
      "Transparent": {
        "thumbColor": "border",
        "thumbBorderColor": "border",
        "hoverThumbColor": "border",
        "hoverThumbBorderColor": "border",
        "hoverTrackColor": "altBackground"
      },
      "thumbColor": "border",
      "thumbBorderColor": "border",
      "hoverThumbColor": "border",
      "hoverThumbBorderColor": "border",
      "hoverTrackColor": "altBackground",
      "Mac": {
        "Transparent": {
          "thumbColor": "border",
          "thumbBorderColor": "border",
          "hoverThumbColor": "border",
          "hoverThumbBorderColor": "border",
          "hoverTrackColor": "altBackground"
        },
        "thumbColor": "border",
        "thumbBorderColor": "border",
        "hoverThumbColor": "border",
        "hoverThumbBorderColor": "border",
        "hoverTrackColor": "altBackground"
      }
    },
    "SearchEverywhere": {
      "Tab": {
        "selectedForeground": "foreground",
        "selectedBackground": "background"
      },
      "SearchField": {
        "infoForeground": "foreground",
        "background": "background",
        "borderColor": "border"
      },
      "Advertiser": {
        "background": "background",
        "borderInsets": "3,8,5,0"
      }
    },
    "SearchMatch": {
      "startBackground": "accent",
      "endBackground": "accent"
    },
    "StatusBar.borderColor": "border",
    "TabbedPane": {
      "foreground": "altForeground",
      "background": "background",
      "underlineColor": "accent",
      "tabSelectionHeight": 2,
      "disabledUnderlineColor": "accentShade1",
      "contentAreaColor": "foreground",
      "hoverColor": "background",
      "focusColor": "background"
    },
    "TableHeader": {
      "cellBorder": "5,0,5,0",
      "foreground": "altForeground",
      "background": "background"
    },
    "Table": {
      "foreground": "altForeground",
      "gridColor": "border",
      "dropLineColor": "border",
      "dropLineShortColor": "border",
      "sortIconColor": "accent",
      "stripeColor": "border",
      "lightSelectionForeground": "altForeground",
      "lightSelectionInactiveForeground": "foreground",
      "lightSelectionBackground": "background",
      "lightSelectionInactiveBackground": "background"
    },
    "TextArea": {
      "background": "background",
      "foreground": "altForeground"
    },
    "TextField": {
      "background": "background",
      "foreground": "altForeground"
    },
    "ToggleButton": {
      "background": "background",
      "foreground": "foreground",
      "onForeground": "background",
      "onBackground": "green",
      "offForeground": "background",
      "offBackground": "disabled",
      "buttonColor": "foreground",
      "borderColor": "foreground"
    },
    "ToolBar": {
      "background": "background",
      "borderHandleColor": "border"
    },
    "ToolTip": {
      "foreground": "altForeground",
      "background": "background",
      "Actions.background": "background"
    },
    "ToolWindow": {
      "Header": {
        "borderColor": "border",
        "background": "background",
        "inactiveBackground": "background"
      },
      "HeaderTab": {
        "selectedInactiveBackground": "background",
        "hoverBackground": "background",
        "hoverInactiveBackground": "background",
        "underlineColor": "accent",
        "inactiveUnderlineColor": "accentShade1",
        "underlinedTabBackground": "background",
        "underlinedTabInactiveBackground": "background",
        "underlineHeight": 2
      },
      "Button": {
        "hoverBackground": "accentShade1",
        "selectedBackground": "altBackground",
        "selectedForeground": "altForeground"
      }
    },
    "Tree": {
      "foreground": "foreground",
      "rowHeight": 22,
      "modifiedItemForeground": "modified",
      "errorForeground": "conflict",
      "selectionBackground": "accentShade2",
      "selectionInactiveBackground": "accentShade3"
    },
    "ValidationTooltip": {
      "errorBackground": "red",
      "errorBorderColor": "red",
      "warningBackground": "orange",
      "warningBorderColor": "orange"
    },
    "VersionControl": {
      "Log.Commit": {
        "currentBranchBackground": "background",
        "unmatchedForeground": "red"
      },
      "RefLabel": {
        "backgroundBase": "blue",
        "backgroundBrightness": 0.4
      },
      "FileHistory.Commit.selectedBranchBackground": "#0D0D40"
    },
    "WelcomeScreen": {
      "Projects.selectionInactiveBackground": "background",
      "separatorColor": "border"
    },
    "Window.border": "1,1,1,1,383C40"
  }
}